README.rst
setup.py
ftweet/__init__.py
ftweet/__main__.py
ftweet/tweet.py
ftweet/version.py
ftweet.egg-info/PKG-INFO
ftweet.egg-info/SOURCES.txt
ftweet.egg-info/dependency_links.txt
ftweet.egg-info/requires.txt
ftweet.egg-info/top_level.txt
scripts/ftweet