Metadata-Version: 1.0
Name: ftweet
Version: 1.1
Summary: A simple python script to tweet status updates from the command line.
Home-page: https://gitlab.com/srfilipek/ftweet
Author: Stefan R. Filipek
Author-email: srfilipek@gmail.com
License: MIT
Keywords: twitter,tweet,commandline,file
Platform: UNKNOWN
